academics_scholar_scraper/__init__.py
academics_scholar_scraper/academics_scholar_scraper.py
academics_scholar_scraper/openai_summarizer.py
academics_scholar_scraper-0.1.1.dist-info/LICENSE
academics_scholar_scraper-0.1.1.dist-info/METADATA
academics_scholar_scraper-0.1.1.dist-info/WHEEL
academics_scholar_scraper-0.1.1.dist-info/entry_points.txt
academics_scholar_scraper-0.1.1.dist-info/top_level.txt
academics_scholar_scraper-0.1.1.dist-info/RECORD
