Metadata-Version: 2.1
Name: academics-scholar-scraper
Version: 0.1.1
Summary: A Python package for scraping scholarly articles
Home-page: https://github.com/TheAcademicsFieldGuideToWritingCode/ScholarScraper
Author: Nathan Laundry
Author-email: nathan.laundry@gmail.com
License-File: LICENSE
Requires-Dist: argparse
Requires-Dist: requests
Requires-Dist: tqdm
Requires-Dist: openai
